scarfer/__main__.py
scarfer/analyzer.py
scarfer/config.py
scarfer/filter_utils.py
scarfer/scan_interface.py
scarfer/format/__init__.py
scarfer/format/factory.py
scarfer/format/format_json.py
scarfer/format/format_markdown.py
scarfer/format/format_text.py
scarfer/format/format_utils.py
scarfer/format/format_yaml.py
scarfer/format/interface.py
scarfer/var/default-exclude-files.txt
scarfer/var/normalized-scan.json
scarfer-0.5.8.dist-info/GPL-3.0-or-later.txt
scarfer-0.5.8.dist-info/METADATA
scarfer-0.5.8.dist-info/WHEEL
scarfer-0.5.8.dist-info/entry_points.txt
scarfer-0.5.8.dist-info/top_level.txt
scarfer-0.5.8.dist-info/RECORD
