Metadata-Version: 2.1
Name: scarfer
Version: 0.5.8
Home-page: https://github.com/hesa/scarfer
Author: Henrik Sanklef
Author-email: hesa@sandklef.com
Classifier: Development Status :: 4 - Beta
Classifier: Environment :: Console
Classifier: Intended Audience :: Developers
Classifier: Intended Audience :: Legal Industry
Classifier: License :: OSI Approved :: GNU General Public License v3 or later (GPLv3+)
Classifier: Natural Language :: English
Classifier: Operating System :: POSIX :: Linux
Classifier: Programming Language :: Python :: 3 :: Only
Classifier: Programming Language :: Python :: 3.6
Classifier: Programming Language :: Python :: 3.7
Classifier: Programming Language :: Python :: 3.8
Classifier: Programming Language :: Python :: 3.9
Classifier: Programming Language :: Python :: 3.10
Classifier: Programming Language :: Python :: 3
Classifier: Topic :: Software Development :: Quality Assurance
Requires-Python: >=3.6
License-File: LICENSES/GPL-3.0-or-later.txt
Requires-Dist: PyYAML
Requires-Dist: flict
Requires-Dist: jsonschema
Requires-Dist: license-expression
Provides-Extra: dev
Requires-Dist: bump2version ; extra == 'dev'
Requires-Dist: flake8 ; extra == 'dev'
Requires-Dist: pytest ; extra == 'dev'
